hdhog/CHANGES.txt
hdhog/__init__.py
hdhog/catalogue.py
hdhog/container.py
hdhog/fsaction.py
hdhog/gui.py
hdhog/logger.py
hdhog/tree.py
hdhog-1.4.0.data/scripts/hdhog
hdhog-1.4.0.dist-info/LICENSE
hdhog-1.4.0.dist-info/METADATA
hdhog-1.4.0.dist-info/WHEEL
hdhog-1.4.0.dist-info/top_level.txt
hdhog-1.4.0.dist-info/RECORD
