Metadata-Version: 2.1
Name: hdhog
Version: 1.4.0
Summary: Find and delete big disk space consumers
Home-page: https://github.com/mafleischer/HDHog
Author: Maurizio Fleischer
Author-email: maurizio.fleischer@web.de
License: GNU General Public License v3 (GPLv3)
Project-URL: Bug Tracker, https://github.com/mafleischer/HDHog/issues
Classifier: Programming Language :: Python :: 3
Classifier: Programming Language :: Python :: 3.6
Classifier: Programming Language :: Python :: 3.7
Classifier: Programming Language :: Python :: 3.8
Classifier: Programming Language :: Python :: 3.9
Classifier: Programming Language :: Python :: 3.10
Classifier: Intended Audience :: System Administrators
Classifier: Intended Audience :: End Users/Desktop
Classifier: License :: OSI Approved :: GNU General Public License v3 (GPLv3)
Classifier: Operating System :: OS Independent
Requires-Python: >=3.6
License-File: LICENSE
Requires-Dist: sortedcontainers
Requires-Dist: anytree
Provides-Extra: test
Requires-Dist: pytest ; extra == 'test'
Requires-Dist: pytest-cov ; extra == 'test'
